missensemble/__init__.py
missensemble/criteria.py
missensemble/miss_ensemble.py
missensemble/models.py
missensemble-0.1.9.dist-info/METADATA
missensemble-0.1.9.dist-info/WHEEL
missensemble-0.1.9.dist-info/licenses/LICENSE
missensemble-0.1.9.dist-info/RECORD
