Metadata-Version: 2.4
Name: missensemble
Version: 0.1.9
Summary: A package for missing data imputation
License: Apache-2.0
License-File: LICENSE
Author: Dimitris Katsimpokis
Author-email: dimi.katsimpokis@gmail.com
Requires-Python: >=3.11,<4.0
Classifier: License :: OSI Approved :: Apache Software License
Classifier: Programming Language :: Python :: 3
Classifier: Programming Language :: Python :: 3.11
Classifier: Programming Language :: Python :: 3.12
Classifier: Programming Language :: Python :: 3.13
Classifier: Programming Language :: Python :: 3.14
Requires-Dist: matplotlib (>=3.10.3,<4.0.0)
Requires-Dist: numpy (>=2.3.2,<3.0.0)
Requires-Dist: pandas (>=2.3.1,<3.0.0)
Requires-Dist: poetry-dynamic-versioning (>=1.9.1,<2.0.0)
Requires-Dist: pytest (>=8.4.1,<9.0.0)
Requires-Dist: scikit-learn (>=1.7.1,<2.0.0)
Requires-Dist: seaborn (>=0.13.2,<0.14.0)
Requires-Dist: xgboost (>=3.0.2,<4.0.0)
Project-URL: Homepage, https://github.com/dkatsimpokis/MissEnsemble
